Topsis_Harsh_101917120/__init__.py
Topsis_Harsh_101917120/topsis.py
Topsis_Harsh_101917120-0.1.dist-info/METADATA
Topsis_Harsh_101917120-0.1.dist-info/WHEEL
Topsis_Harsh_101917120-0.1.dist-info/top_level.txt
Topsis_Harsh_101917120-0.1.dist-info/RECORD
