Metadata-Version: 2.1
Name: Topsis-Harsh-101917120
Version: 0.1
Summary: Topsis package
Home-page: UNKNOWN
Author: Harsh Mishra
Author-email: hmishra_be19@thapar.edu
License: MIT
Keywords: topsis,Rank,Best,Model
Platform: UNKNOWN
Classifier: Programming Language :: Python :: 3
Classifier: License :: OSI Approved :: MIT License
Classifier: Operating System :: OS Independent
Requires-Dist: numpy
Requires-Dist: pandas
